{"albums":[{"artist":"Chastity","album":"Death Lust","date":"Jul 14 2018"},{"artist":"BodyHead","album":"The Switch","date":"Jul 13 2018"},{"artist":"Deafheaven","album":"Ordinary Corrupt Human Love","date":"Jul 13 2018"},{"artist":"Haron","album":"Wandelaar","date":"Jul 11 2018"},{"artist":"Future","album":"BEASTMODE 2","date":"Jul 11 2018"},{"artist":"Luluc","album":"Sculptor","date":"Jul 13 2018"},{"artist":"Cowboy Junkies","album":"All That Reckoning","date":"Jul 13 2018"},{"artist":"Pariah","album":"Here From Where We Are","date":"Jul 13 2018"},{"artist":"Miss Red","album":"KO","date":"Jul 13 2018"},{"artist":"Between The Buried And Me","album":"Automata II","date":"Jul 13 2018"}]}
